Workbook
Name Slicer_Region: #N/A
Name Slicer_Segment: #N/A
Name Slicer_Year: #N/A

Sheet Combo Chart
A3: Row Labels | B3: Sum of Sales | C3: Sum of Profit
A4: Jan | B4: 3187.336 | C4: 590.6891
A5: Feb | B5: 1010.974 | C5: 256.7308
A6: Mar | B6: 5756.109 | C6: 1505.028
A7: Apr | B7: 9769.418 | C7: 1168.5853
A8: May | B8: 10200.95 | C8: 2813.6312
A9: Jun | B9: 6433.407 | C9: 555.8316
A10: Jul | B10: 2780.753 | C10: 371.0148
A11: Aug | B11: 5923.5565 | C11: 1353.8364
A12: Sep | B12: 4142.205 | C12: 622.9454
A13: Oct | B13: 5899.087 | C13: 875.443
A14: Nov | B14: 17620.47 | C14: 2554.9699
A15: Dec | B15: 6762.675 | C15: 1027.2772
A16: Grand Total | B16: 79486.94 | C16: 13695.983

Sheet Waterfall Chart
A3: Row Labels | B3: Sum of Profit | D3: Category | E3: Profit
A4: Technology | B4: 6967.5555 | D4: =A4 -> Technology | E4: =GETPIVOTDATA("Profit",$A$3,"Category",A4) -> 6967.5555
A5: Office Supplies | B5: 4862.3198 | D5: =A5 -> Office Supplies | E5: =GETPIVOTDATA("Profit",$A$3,"Category",A5) -> 4862.3198
A6: Furniture | B6: 1866.1074 | D6: =A6 -> Furniture | E6: =GETPIVOTDATA("Profit",$A$3,"Category",A6) -> 1866.1074
A7: Grand Total | B7: 13695.983 | D7: =A7 -> Grand Total | E7: =GETPIVOTDATA("Profit",$A$3) -> 13695.983

Sheet Pie Chart
A3: Row Labels | B3: Sum of Sales
A4: Furniture | B4: 0.27518735
A5: Office Supplies | B5: 0.39845357
A6: Technology | B6: 0.32635908
A7: Grand Total | B7: 1

Sheet Map Chart
A3: Row Labels | B3: Sum of Sales | D3: State | E3: Sales
A4: Alabama | B4: 10407.21 | D4: =A4 -> Alabama | E4: =GETPIVOTDATA("Sales",$A$3,"State",A4) -> 10407.21
A5: Arkansas | B5: 1106.36 | D5: =A5 -> Arkansas | E5: =GETPIVOTDATA("Sales",$A$3,"State",A5) -> 1106.36
A6: Florida | B6: 17075.483 | D6: =A6 -> Florida | E6: =GETPIVOTDATA("Sales",$A$3,"State",A6) -> 17075.483
A7: Georgia | B7: 6311.58 | D7: =A7 -> Georgia | E7: =GETPIVOTDATA("Sales",$A$3,"State",A7) -> 6311.58
A8: Kentucky | B8: 3654.66 | D8: =A8 -> Kentucky | E8: =GETPIVOTDATA("Sales",$A$3,"State",A8) -> 3654.66
A9: Louisiana | B9: 1882.35 | D9: =A9 -> Louisiana | E9: =GETPIVOTDATA("Sales",$A$3,"State",A9) -> 1882.35
A10: Mississippi | B10: 523.47 | D10: =A10 -> Mississippi | E10: =GETPIVOTDATA("Sales",$A$3,"State",A10) -> 523.47
A11: North Carolina | B11: 6099.74 | D11: =A11 -> North Carolina | E11: =GETPIVOTDATA("Sales",$A$3,"State",A11) -> 6099.74
A12: South Carolina | B12: 1681.13 | D12: =A12 -> South Carolina | E12: =GETPIVOTDATA("Sales",$A$3,"State",A12) -> 1681.13
A13: Tennessee | B13: 4309.318 | D13: =A13 -> Tennessee | E13: =GETPIVOTDATA("Sales",$A$3,"State",A13) -> 4309.318
A14: Virginia | B14: 26435.64 | D14: =A14 -> Virginia | E14: =GETPIVOTDATA("Sales",$A$3,"State",A14) -> 26435.64
A15: Grand Total | B15: 79486.94 | D15: =A15 -> Grand Total | E15: =GETPIVOTDATA("Sales",$A$3) -> 79486.94

Sheet Top 5
A3: Row Labels | B3: Sum of Sales
A4: Binders | B4: 8071.025
A5: Storage | B5: 8406.238
A6: Tables | B6: 8504.8785
A7: Chairs | B7: 8610.952
A8: Phones | B8: 13508.912
A9: Grand Total | B9: 47102.006

Sheet KPI
A3: Row Labels | B3: Sum of Sales | D3: Row Labels | E3: Sum of Profit | G3: Row Labels | H3: Sum of Quantity | J3: Row Labels | K3: Count of Order ID | M3: Row Labels | N3: Sum of Profit Margin
A4: Jan | B4: 3187.336 | D4: Jan | E4: 590.6891 | G4: Jan | H4: 64 | J4: Jan | K4: 17 | M4: Jan | N4: 0.18532376
A5: Feb | B5: 1010.974 | D5: Feb | E5: 256.7308 | G5: Feb | H5: 34 | J5: Feb | K5: 9 | M5: Feb | N5: 0.25394402
A6: Mar | B6: 5756.109 | D6: Mar | E6: 1505.028 | G6: Mar | H6: 121 | J6: Mar | K6: 38 | M6: Mar | N6: 0.26146621
A7: Apr | B7: 9769.418 | D7: Apr | E7: 1168.5853 | G7: Apr | H7: 107 | J7: Apr | K7: 27 | M7: Apr | N7: 0.11961668
A8: May | B8: 10200.95 | D8: May | E8: 2813.6312 | G8: May | H8: 164 | J8: May | K8: 36 | M8: May | N8: 0.27582051
A9: Jun | B9: 6433.407 | D9: Jun | E9: 555.8316 | G9: Jun | H9: 107 | J9: Jun | K9: 30 | M9: Jun | N9: 0.086397705
A10: Jul | B10: 2780.753 | D10: Jul | E10: 371.0148 | G10: Jul | H10: 115 | J10: Jul | K10: 30 | M10: Jul | N10: 0.13342242
A11: Aug | B11: 5923.5565 | D11: Aug | E11: 1353.8364 | G11: Aug | H11: 117 | J11: Aug | K11: 28 | M11: Aug | N11: 0.22855128
A12: Sep | B12: 4142.205 | D12: Sep | E12: 622.9454 | G12: Sep | H12: 146 | J12: Sep | K12: 35 | M12: Sep | N12: 0.1503898
A13: Oct | B13: 5899.087 | D13: Oct | E13: 875.443 | G13: Oct | H13: 86 | J13: Oct | K13: 23 | M13: Oct | N13: 0.14840313
A14: Nov | B14: 17620.47 | D14: Nov | E14: 2554.9699 | G14: Nov | H14: 269 | J14: Nov | K14: 62 | M14: Nov | N14: 0.1450001
A15: Dec | B15: 6762.675 | D15: Dec | E15: 1027.2772 | G15: Dec | H15: 148 | J15: Dec | K15: 36 | M15: Dec | N15: 0.15190397
A16: Grand Total | B16: 79486.94 | D16: Grand Total | E16: 13695.983 | G16: Grand Total | H16: 1478 | J16: Grand Total | K16: 371 | M16: Grand Total | N16: 0.17230482
B17: =GETPIVOTDATA("Sales",$A$3) -> 79486.94 | E17: =GETPIVOTDATA("Profit",$D$3) -> 13695.983 | H17: =GETPIVOTDATA("Quantity",$G$3) -> 1478 | K17: =GETPIVOTDATA("Order ID",$J$3) -> 371 | N17: =GETPIVOTDATA("Profit Margin",$M$3) -> 0.17230482

Sheet KPI YOY
A3: Row Labels | B3: Sum of Sales | C3: Sum of Profit | D3: Sum of Quantity | E3: Count of Order ID | F3: Sum of Profit Margin
A4: 2011 | B4: 34684.72 | C4: 7702.1539 | D4: 525 | E4: 141 | F4: 0.22206187
A5: 2012 | B5: 18107.33 | C5: 1896.3236 | D5: 496 | E5: 121 | F5: 0.10472685
A6: 2013 | B6: 26694.891 | C6: 4097.5052 | D6: 457 | E6: 109 | F6: 0.15349399
A7: 2014 | B7: 42398.992 | C7: 1519.2405 | D7: 538 | E7: 139 | F7: 0.035831996
H8: =(GETPIVOTDATA("Sum of Sales",$A$3,"Years (Order Date)",2014)/GETPIVOTDATA("Sum of Sales",$A$3,"Years (Order Date)",2013))-1 -> 0.58828117 | I8: =(GETPIVOTDATA("Sum of Profit",$A$3,"Years (Order Date)",2014)/GETPIVOTDATA("Sum of Profit",$A$3,"Years (Order Date)",2013))-1 -> -0.62922793 | J8: =(GETPIVOTDATA("Sum of Quantity",$A$3,"Years (Order Date)",2014)/GETPIVOTDATA("Sum of Quantity",$A$3,"Years (Order Date)",2013))-1 -> 0.17724289 | K8: =(GETPIVOTDATA("Count of Order ID",$A$3,"Years (Order Date)",2014)/GETPIVOTDATA("Count of Order ID",$A$3,"Years (Order Date)",2013))-1 -> 0.27522936 | L8: =(GETPIVOTDATA("Sum of Profit Margin",$A$3,"Years (Order Date)",2014)/GETPIVOTDATA("Sum of Profit Margin",$A$3,"Years (Order Date)",2013))-1 -> -0.76655766

Sheet Dashboard

Sheet Data
A1: Row ID | B1: Order ID | C1: Year | D1: Order Date | E1: Ship Date | F1: Ship Mode | G1: Customer ID | H1: Customer Name | I1: Segment | J1: Country | K1: City | L1: State | M1: Postal Code | N1: Region | O1: Product ID | P1: Category | Q1: Sub-Category | R1: Product Name | S1: Sales | T1: Quantity | U1: Discount | V1: Profit
A2: 1 | B2: CA-2013-152156 | C2: =YEAR(Data!$D2) -> 2013 | D2: 41587 | E2: 41590 | F2: Second Class | G2: CG-12520 | H2: Claire Gute | I2: Consumer | J2: United States | K2: Henderson | L2: Kentucky | M2: 42420 | N2: South | O2: FUR-BO-10001798 | P2: Furniture | Q2: Bookcases | R2: Bush Somerset Collection Bookcase | S2: 261.96 | T2: 2 | U2: 0 | V2: 41.9136
A3: 2 | B3: CA-2013-152156 | C3: =YEAR(Data!$D3) -> 2013 | D3: 41587 | E3: 41590 | F3: Second Class | G3: CG-12520 | H3: Claire Gute | I3: Consumer | J3: United States | K3: Henderson | L3: Kentucky | M3: 42420 | N3: South | O3: FUR-CH-10000454 | P3: Furniture | Q3: Chairs | R3: Hon Deluxe Fabric Upholstered Stacking Chairs, Rounded Back | S3: 731.94 | T3: 3 | U3: 0 | V3: 219.582
A4: 3 | B4: CA-2013-138688 | C4: =YEAR(Data!$D4) -> 2013 | D4: 41438 | E4: 41442 | F4: Second Class | G4: DV-13045 | H4: Darrin Van Huff | I4: Corporate | J4: United States | K4: Los Angeles | L4: California | M4: 90036 | N4: West | O4: OFF-LA-10000240 | P4: Office Supplies | Q4: Labels | R4: Self-Adhesive Address Labels for Typewriters by Universal | S4: 14.62 | T4: 2 | U4: 0 | V4: 6.8714
A5: 4 | B5: US-2012-108966 | C5: =YEAR(Data!$D5) -> 2012 | D5: 41193 | E5: 41200 | F5: Standard Class | G5: SO-20335 | H5: Sean O'Donnell | I5: Consumer | J5: United States | K5: Fort Lauderdale | L5: Florida | M5: 33311 | N5: South | O5: FUR-TA-10000577 | P5: Furniture | Q5: Tables | R5: Bretford CR4500 Series Slim Rectangular Table | S5: 957.5775 | T5: 5 | U5: 0.45 | V5: -383.031
A6: 5 | B6: US-2012-108966 | C6: =YEAR(Data!$D6) -> 2012 | D6: 41193 | E6: 41200 | F6: Standard Class | G6: SO-20335 | H6: Sean O'Donnell | I6: Consumer | J6: United States | K6: Fort Lauderdale | L6: Florida | M6: 33311 | N6: South | O6: OFF-ST-10000760 | P6: Office Supplies | Q6: Storage | R6: Eldon Fold 'N Roll Cart System | S6: 22.368 | T6: 2 | U6: 0.2 | V6: 2.5164
A7: 6 | B7: CA-2011-115812 | C7: =YEAR(Data!$D7) -> 2011 | D7: 40703 | E7: 40708 | F7: Standard Class | G7: BH-11710 | H7: Brosina Hoffman | I7: Consumer | J7: United States | K7: Los Angeles | L7: California | M7: 90032 | N7: West | O7: FUR-FU-10001487 | P7: Furniture | Q7: Furnishings | R7: Eldon Expressions Wood and Plastic Desk Accessories, Cherry Wood | S7: 48.86 | T7: 7 | U7: 0 | V7: 14.1694
A8: 7 | B8: CA-2011-115812 | C8: =YEAR(Data!$D8) -> 2011 | D8: 40703 | E8: 40708 | F8: Standard Class | G8: BH-11710 | H8: Brosina Hoffman | I8: Consumer | J8: United States | K8: Los Angeles | L8: California | M8: 90032 | N8: West | O8: OFF-AR-10002833 | P8: Office Supplies | Q8: Art | R8: Newell 322 | S8: 7.28 | T8: 4 | U8: 0 | V8: 1.9656
A9: 8 | B9: CA-2011-115812 | C9: =YEAR(Data!$D9) -> 2011 | D9: 40703 | E9: 40708 | F9: Standard Class | G9: BH-11710 | H9: Brosina Hoffman | I9: Consumer | J9: United States | K9: Los Angeles | L9: California | M9: 90032 | N9: West | O9: TEC-PH-10002275 | P9: Technology | Q9: Phones | R9: Mitel 5320 IP Phone VoIP phone | S9: 907.152 | T9: 6 | U9: 0.2 | V9: 90.7152
A10: 9 | B10: CA-2011-115812 | C10: =YEAR(Data!$D10) -> 2011 | D10: 40703 | E10: 40708 | F10: Standard Class | G10: BH-11710 | H10: Brosina Hoffman | I10: Consumer | J10: United States | K10: Los Angeles | L10: California | M10: 90032 | N10: West | O10: OFF-BI-10003910 | P10: Office Supplies | Q10: Binders | R10: DXL Angle-View Binders with Locking Rings by Samsill | S10: 18.504 | T10: 3 | U10: 0.2 | V10: 5.7825
A11: 10 | B11: CA-2011-115812 | C11: =YEAR(Data!$D11) -> 2011 | D11: 40703 | E11: 40708 | F11: Standard Class | G11: BH-11710 | H11: Brosina Hoffman | I11: Consumer | J11: United States | K11: Los Angeles | L11: California | M11: 90032 | N11: West | O11: OFF-AP-10002892 | P11: Office Supplies | Q11: Appliances | R11: Belkin F5C206VTEL 6 Outlet Surge | S11: 114.9 | T11: 5 | U11: 0 | V11: 34.47
A12: 11 | B12: CA-2011-115812 | C12: =YEAR(Data!$D12) -> 2011 | D12: 40703 | E12: 40708 | F12: Standard Class | G12: BH-11710 | H12: Brosina Hoffman | I12: Consumer | J12: United States | K12: Los Angeles | L12: California | M12: 90032 | N12: West | O12: FUR-TA-10001539 | P12: Furniture | Q12: Tables | R12: Chromcraft Rectangular Conference Tables | S12: 1706.184 | T12: 9 | U12: 0.2 | V12: 85.3092
A13: 12 | B13: CA-2011-115812 | C13: =YEAR(Data!$D13) -> 2011 | D13: 40703 | E13: 40708 | F13: Standard Class | G13: BH-11710 | H13: Brosina Hoffman | I13: Consumer | J13: United States | K13: Los Angeles | L13: California | M13: 90032 | N13: West | O13: TEC-PH-10002033 | P13: Technology | Q13: Phones | R13: Konftel 250 Conference phone - Charcoal black | S13: 911.424 | T13: 4 | U13: 0.2 | V13: 68.3568
... A2235: 2234 | B2235: CA-2012-123232 | C2235: =YEAR(Data!$D2235) -> 2012 | D2235: 41257 | E2235: 41259 | F2235: Second Class | G2235: DJ-13630 | H2235: Doug Jacobs | I2235: Consumer | J2235: United States | K2235: Portland | L2235: Oregon | M2235: 97206 | N2235: West | O2235: TEC-PH-10001051 | P2235: Technology | Q2235: Phones | R2235: HTC One | S2235: 319.968 | T2235: 4 | U2235: 0.2 | V2235: 35.9964
A2236: 2235 | B2236: CA-2014-104066 | C2236: =YEAR(Data!$D2236) -> 2014 | D2236: 41979 | E2236: 41984 | F2236: Standard Class | G2236: QJ-19255 | H2236: Quincy Jones | I2236: Corporate | J2236: United States | K2236: Burlington | L2236: Vermont | M2236: 05408 | N2236: East | O2236: TEC-AC-10001013 | P2236: Technology | Q2236: Accessories | R2236: Logitech ClearChat Comfort/USB Headset H390 | S2236: 205.03 | T2236: 7 | U2236: 0 | V2236: 67.6599
A2237: 2236 | B2237: CA-2012-145849 | C2237: =YEAR(Data!$D2237) -> 2012 | D2237: 41167 | E2237: 41169 | F2237: Second Class | G2237: CT-11995 | H2237: Carol Triggs | I2237: Consumer | J2237: United States | K2237: Indianapolis | L2237: Indiana | M2237: 46203 | N2237: Central | O2237: OFF-ST-10000025 | P2237: Office Supplies | Q2237: Storage | R2237: Fellowes Stor/Drawer Steel Plus Storage Drawers | S2237: 190.86 | T2237: 2 | U2237: 0 | V2237: 11.4516
A2238: 2237 | B2238: CA-2012-145849 | C2238: =YEAR(Data!$D2238) -> 2012 | D2238: 41167 | E2238: 41169 | F2238: Second Class | G2238: CT-11995 | H2238: Carol Triggs | I2238: Consumer | J2238: United States | K2238: Indianapolis | L2238: Indiana | M2238: 46203 | N2238: Central | O2238: OFF-AR-10000817 | P2238: Office Supplies | Q2238: Art | R2238: Manco Dry-Lighter Erasable Highlighter | S2238: 24.32 | T2238: 8 | U2238: 0 | V2238: 8.2688
A2239: 2238 | B2239: CA-2013-122322 | C2239: =YEAR(Data!$D2239) -> 2013 | D2239: 41471 | E2239: 41477 | F2239: Standard Class | G2239: RH-19510 | H2239: Rick Huthwaite | I2239: Home Office | J2239: United States | K2239: Provo | L2239: Utah | M2239: 84604 | N2239: West | O2239: OFF-SU-10000952 | P2239: Office Supplies | Q2239: Supplies | R2239: Fiskars Home & Office Scissors | S2239: 44.4 | T2239: 5 | U2239: 0 | V2239: 12.432
A2240: 2239 | B2240: CA-2014-166849 | C2240: =YEAR(Data!$D2240) -> 2014 | D2240: 41750 | E2240: 41756 | F2240: Standard Class | G2240: SJ-20125 | H2240: Sanjit Jacobs | I2240: Home Office | J2240: United States | K2240: Chicago | L2240: Illinois | M2240: 60610 | N2240: Central | O2240: FUR-FU-10004597 | P2240: Furniture | Q2240: Furnishings | R2240: Eldon Cleatmat Chair Mats for Medium Pile Carpets | S2240: 44.4 | T2240: 2 | U2240: 0.6 | V2240: -52.17
A2241: 2240 | B2241: CA-2013-146633 | C2241: =YEAR(Data!$D2241) -> 2013 | D2241: 41594 | E2241: 41596 | F2241: Second Class | G2241: TG-21310 | H2241: Toby Gnade | I2241: Consumer | J2241: United States | K2241: Los Angeles | L2241: California | M2241: 90049 | N2241: West | O2241: OFF-BI-10003527 | P2241: Office Supplies | Q2241: Binders | R2241: Fellowes PB500 Electric Punch Plastic Comb Binding Machine with Manual Bind | S2241: 1016.792 | T2241: 1 | U2241: 0.2 | V2241: 381.297
A2242: 2241 | B2242: CA-2013-146633 | C2242: =YEAR(Data!$D2242) -> 2013 | D2242: 41594 | E2242: 41596 | F2242: Second Class | G2242: TG-21310 | H2242: Toby Gnade | I2242: Consumer | J2242: United States | K2242: Los Angeles | L2242: California | M2242: 90049 | N2242: West | O2242: OFF-BI-10002982 | P2242: Office Supplies | Q2242: Binders | R2242: Avery Self-Adhesive Photo Pockets for Polaroid Photos | S2242: 38.136 | T2242: 7 | U2242: 0.2 | V2242: 13.3476
A2243: 2242 | B2243: US-2013-126893 | C2243: =YEAR(Data!$D2243) -> 2013 | D2243: 41605 | E2243: 41610 | F2243: Standard Class | G2243: CT-11995 | H2243: Carol Triggs | I2243: Consumer | J2243: United States | K2243: Philadelphia | L2243: Pennsylvania | M2243: 19134 | N2243: East | O2243: TEC-PH-10004165 | P2243: Technology | Q2243: Phones | R2243: Mitel MiVoice 5330e IP Phone | S2243: 494.982 | T2243: 3 | U2243: 0.4 | V2243: -115.4958
A2244: 2243 | B2244: CA-2014-103380 | C2244: =YEAR(Data!$D2244) -> 2014 | D2244: 41965 | E2244: 41969 | F2244: Standard Class | G2244: BF-11005 | H2244: Barry Franz | I2244: Home Office | J2244: United States | K2244: Pasadena | L2244: California | M2244: 91104 | N2244: West | O2244: OFF-ST-10003442 | P2244: Office Supplies | Q2244: Storage | R2244: Eldon Portable Mobile Manager | S2244: 56.56 | T2244: 2 | U2244: 0 | V2244: 15.2712
A2245: 2244 | B2245: CA-2014-103380 | C2245: =YEAR(Data!$D2245) -> 2014 | D2245: 41965 | E2245: 41969 | F2245: Standard Class | G2245: BF-11005 | H2245: Barry Franz | I2245: Home Office | J2245: United States | K2245: Pasadena | L2245: California | M2245: 91104 | N2245: West | O2245: OFF-AR-10003856 | P2245: Office Supplies | Q2245: Art | R2245: Newell 344 | S2245: 5.56 | T2245: 2 | U2245: 0 | V2245: 1.4456
A2246: 2245 | B2246: CA-2014-103380 | C2246: =YEAR(Data!$D2246) -> 2014 | D2246: 41965 | E2246: 41969 | F2246: Standard Class | G2246: BF-11005 | H2246: Barry Franz | I2246: Home Office | J2246: United States | K2246: Pasadena | L2246: California | M2246: 91104 | N2246: West | O2246: OFF-FA-10004248 | P2246: Office Supplies | Q2246: Fasteners | R2246: Advantus T-Pin Paper Clips | S2246: 9.02 | T2246: 2 | U2246: 0 | V2246: 3.5178
A2247: 2246 | B2247: CA-2014-103380 | C2247: =YEAR(Data!$D2247) -> 2014 | D2247: 41965 | E2247: 41969 | F2247: Standard Class | G2247: BF-11005 | H2247: Barry Franz | I2247: Home Office | J2247: United States | K2247: Pasadena | L2247: California | M2247: 91104 | N2247: West | O2247: OFF-AP-10001492 | P2247: Office Supplies | Q2247: Appliances | R2247: Acco Six-Outlet Power Strip, 4' Cord Length | S2247: 8.62 | T2247: 1 | U2247: 0 | V2247: 2.2412
A2248: 2247 | B2248: CA-2014-103380 | C2248: =YEAR(Data!$D2248) -> 2014 | D2248: 41965 | E2248: 41969 | F2248: Standard Class | G2248: BF-11005 | H2248: Barry Franz | I2248: Home Office | J2248: United States | K2248: Pasadena | L2248: California | M2248: 91104 | N2248: West | O2248: TEC-PH-10004165 | P2248: Technology | Q2248: Phones | R2248: Mitel MiVoice 5330e IP Phone | S2248: 659.976 | T2248: 3 | U2248: 0.2 | V2248: 49.4982
... A5275: 5274 | B5275: US-2013-158309 | C5275: =YEAR(Data!$D5275) -> 2013 | D5275: 41605 | E5275: 41608 | F5275: First Class | G5275: PA-19060 | H5275: Pete Armstrong | I5275: Home Office | J5275: United States | K5275: Miami | L5275: Florida | M5275: 33142 | N5275: South | O5275: OFF-BI-10000145 | P5275: Office Supplies | Q5275: Binders | R5275: Zipper Ring Binder Pockets | S5275: 3.744 | T5275: 4 | U5275: 0.7 | V5275: -2.6208
A5276: 5275 | B5276: CA-2012-162887 | C5276: =YEAR(Data!$D5276) -> 2012 | D5276: 41220 | E5276: 41222 | F5276: Second Class | G5276: SV-20785 | H5276: Stewart Visinsky | I5276: Consumer | J5276: United States | K5276: Burlington | L5276: Vermont | M5276: 05408 | N5276: East | O5276: FUR-CH-10000595 | P5276: Furniture | Q5276: Chairs | R5276: Safco Contoured Stacking Chairs | S5276: 715.2 | T5276: 3 | U5276: 0 | V5276: 178.8
A5277: 5276 | B5277: CA-2014-147333 | C5277: =YEAR(Data!$D5277) -> 2014 | D5277: 41988 | E5277: 41994 | F5277: Standard Class | G5277: KL-16555 | H5277: Kelly Lampkin | I5277: Corporate | J5277: United States | K5277: Fayetteville | L5277: Arkansas | M5277: 72701 | N5277: South | O5277: TEC-AC-10004469 | P5277: Technology | Q5277: Accessories | R5277: Microsoft Sculpt Comfort Mouse | S5277: 159.8 | T5277: 4 | U5277: 0 | V5277: 70.312
A5278: 5277 | B5278: CA-2014-147333 | C5278: =YEAR(Data!$D5278) -> 2014 | D5278: 41988 | E5278: 41994 | F5278: Standard Class | G5278: KL-16555 | H5278: Kelly Lampkin | I5278: Corporate | J5278: United States | K5278: Fayetteville | L5278: Arkansas | M5278: 72701 | N5278: South | O5278: TEC-AC-10003038 | P5278: Technology | Q5278: Accessories | R5278: Kingston Digital DataTraveler 16GB USB 2.0 | S5278: 44.75 | T5278: 5 | U5278: 0 | V5278: 8.5025
A5279: 5278 | B5279: CA-2011-113859 | C5279: =YEAR(Data!$D5279) -> 2011 | D5279: 40799 | E5279: 40803 | F5279: Standard Class | G5279: BC-11125 | H5279: Becky Castell | I5279: Home Office | J5279: United States | K5279: Odessa | L5279: Texas | M5279: 79762 | N5279: Central | O5279: FUR-CH-10004698 | P5279: Furniture | Q5279: Chairs | R5279: Padded Folding Chairs, Black, 4/Carton | S5279: 340.116 | T5279: 6 | U5279: 0.3 | V5279: -9.7176
A5280: 5279 | B5280: CA-2011-159681 | C5280: =YEAR(Data!$D5280) -> 2011 | D5280: 40884 | E5280: 40890 | F5280: Standard Class | G5280: PO-18850 | H5280: Patrick O'Brill | I5280: Consumer | J5280: United States | K5280: Virginia Beach | L5280: Virginia | M5280: 23464 | N5280: South | O5280: OFF-PA-10003641 | P5280: Office Supplies | Q5280: Paper | R5280: Xerox 1909 | S5280: 105.52 | T5280: 4 | U5280: 0 | V5280: 48.5392
A5281: 5280 | B5281: US-2014-104094 | C5281: =YEAR(Data!$D5281) -> 2014 | D5281: 41890 | E5281: 41894 | F5281: Standard Class | G5281: AG-10675 | H5281: Anna Gayman | I5281: Consumer | J5281: United States | K5281: Milwaukee | L5281: Wisconsin | M5281: 53209 | N5281: Central | O5281: TEC-AC-10002134 | P5281: Technology | Q5281: Accessories | R5281: Rosewill 107 Normal Keys USB Wired Standard Keyboard | S5281: 13.48 | T5281: 1 | U5281: 0 | V5281: 1.8872
A5282: 5281 | B5282: CA-2014-152709 | C5282: =YEAR(Data!$D5282) -> 2014 | D5282: 41920 | E5282: 41925 | F5282: Standard Class | G5282: DB-13210 | H5282: Dean Braden | I5282: Consumer | J5282: United States | K5282: Detroit | L5282: Michigan | M5282: 48234 | N5282: Central | O5282: OFF-ST-10001837 | P5282: Office Supplies | Q5282: Storage | R5282: SAFCO Mobile Desk Side File, Wire Frame | S5282: 85.52 | T5282: 2 | U5282: 0 | V5282: 22.2352
A5283: 5282 | B5283: CA-2012-105158 | C5283: =YEAR(Data!$D5283) -> 2012 | D5283: 41157 | E5283: 41162 | F5283: Standard Class | G5283: SP-20860 | H5283: Sung Pak | I5283: Corporate | J5283: United States | K5283: Rochester | L5283: Minnesota | M5283: 55901 | N5283: Central | O5283: FUR-FU-10001706 | P5283: Furniture | Q5283: Furnishings | R5283: Longer-Life Soft White Bulbs | S5283: 6.16 | T5283: 2 | U5283: 0 | V5283: 2.9568
A5284: 5283 | B5284: CA-2012-105158 | C5284: =YEAR(Data!$D5284) -> 2012 | D5284: 41157 | E5284: 41162 | F5284: Standard Class | G5284: SP-20860 | H5284: Sung Pak | I5284: Corporate | J5284: United States | K5284: Rochester | L5284: Minnesota | M5284: 55901 | N5284: Central | O5284: OFF-PA-10001970 | P5284: Office Supplies | Q5284: Paper | R5284: Xerox 1881 | S5284: 36.84 | T5284: 3 | U5284: 0 | V5284: 17.3148
A5285: 5284 | B5285: CA-2011-133424 | C5285: =YEAR(Data!$D5285) -> 2011 | D5285: 40632 | E5285: 40637 | F5285: Standard Class | G5285: Dl-13600 | H5285: Dorris liebe | I5285: Corporate | J5285: United States | K5285: Seattle | L5285: Washington | M5285: 98105 | N5285: West | O5285: OFF-ST-10002957 | P5285: Office Supplies | Q5285: Storage | R5285: Sterilite Show Offs Storage Containers | S5285: 15.84 | T5285: 3 | U5285: 0 | V5285: 0
A5286: 5285 | B5286: CA-2011-133424 | C5286: =YEAR(Data!$D5286) -> 2011 | D5286: 40632 | E5286: 40637 | F5286: Standard Class | G5286: Dl-13600 | H5286: Dorris liebe | I5286: Corporate | J5286: United States | K5286: Seattle | L5286: Washington | M5286: 98105 | N5286: West | O5286: OFF-LA-10002312 | P5286: Office Supplies | Q5286: Labels | R5286: Avery 490 | S5286: 44.4 | T5286: 3 | U5286: 0 | V5286: 22.2
A5287: 5286 | B5287: CA-2014-105991 | C5287: =YEAR(Data!$D5287) -> 2014 | D5287: 41765 | E5287: 41766 | F5287: First Class | G5287: LH-17020 | H5287: Lisa Hazard | I5287: Consumer | J5287: United States | K5287: Louisville | L5287: Colorado | M5287: 80027 | N5287: West | O5287: OFF-EN-10002600 | P5287: Office Supplies | Q5287: Envelopes | R5287: Redi-Strip #10 Envelopes, 4 1/8 x 9 1/2 | S5287: 21.24 | T5287: 9 | U5287: 0.2 | V5287: 7.434
A5288: 5287 | B5288: CA-2014-105991 | C5288: =YEAR(Data!$D5288) -> 2014 | D5288: 41765 | E5288: 41766 | F5288: First Class | G5288: LH-17020 | H5288: Lisa Hazard | I5288: Consumer | J5288: United States | K5288: Louisville | L5288: Colorado | M5288: 80027 | N5288: West | O5288: OFF-BI-10003274 | P5288: Office Supplies | Q5288: Binders | R5288: Avery Durable Slant Ring Binders, No Labels | S5288: 9.552 | T5288: 8 | U5288: 0.7 | V5288: -7.3232
... A8799: 8798 | B8799: CA-2013-106397 | C8799: =YEAR(Data!$D8799) -> 2013 | D8799: 41463 | E8799: 41469 | F8799: Standard Class | G8799: MJ-17740 | H8799: Max Jones | I8799: Consumer | J8799: United States | K8799: Orem | L8799: Utah | M8799: 84057 | N8799: West | O8799: OFF-AR-10004602 | P8799: Office Supplies | Q8799: Art | R8799: Boston KS Multi-Size Manual Pencil Sharpener | S8799: 45.98 | T8799: 2 | U8799: 0 | V8799: 12.8744
A8800: 8799 | B8800: US-2013-150140 | C8800: =YEAR(Data!$D8800) -> 2013 | D8800: 41371 | E8800: 41375 | F8800: Standard Class | G8800: VM-21685 | H8800: Valerie Mitchum | I8800: Home Office | J8800: United States | K8800: Burlington | L8800: Vermont | M8800: 05408 | N8800: East | O8800: TEC-PH-10002555 | P8800: Technology | Q8800: Phones | R8800: Nortel Meridian M5316 Digital phone | S8800: 1294.75 | T8800: 5 | U8800: 0 | V8800: 336.635
A8801: 8800 | B8801: CA-2011-116666 | C8801: =YEAR(Data!$D8801) -> 2011 | D8801: 40671 | E8801: 40673 | F8801: First Class | G8801: KT-16480 | H8801: Kean Thornton | I8801: Consumer | J8801: United States | K8801: Philadelphia | L8801: Pennsylvania | M8801: 19134 | N8801: East | O8801: TEC-CO-10001449 | P8801: Technology | Q8801: Copiers | R8801: Hewlett Packard LaserJet 3310 Copier | S8801: 1799.97 | T8801: 5 | U8801: 0.4 | V8801: 239.996
A8802: 8801 | B8802: CA-2014-148992 | C8802: =YEAR(Data!$D8802) -> 2014 | D8802: 41967 | E8802: 41971 | F8802: Standard Class | G8802: CS-12250 | H8802: Chris Selesnick | I8802: Corporate | J8802: United States | K8802: Chicago | L8802: Illinois | M8802: 60623 | N8802: Central | O8802: OFF-PA-10004285 | P8802: Office Supplies | Q8802: Paper | R8802: Xerox 1959 | S8802: 10.688 | T8802: 2 | U8802: 0.2 | V8802: 3.7408
A8803: 8802 | B8803: CA-2013-140935 | C8803: =YEAR(Data!$D8803) -> 2013 | D8803: 41589 | E8803: 41591 | F8803: First Class | G8803: AB-10015 | H8803: Aaron Bergman | I8803: Consumer | J8803: United States | K8803: Oklahoma City | L8803: Oklahoma | M8803: 73120 | N8803: Central | O8803: TEC-PH-10000562 | P8803: Technology | Q8803: Phones | R8803: Samsung Convoy 3 | S8803: 221.98 | T8803: 2 | U8803: 0 | V8803: 62.1544
A8804: 8803 | B8804: CA-2013-140935 | C8804: =YEAR(Data!$D8804) -> 2013 | D8804: 41589 | E8804: 41591 | F8804: First Class | G8804: AB-10015 | H8804: Aaron Bergman | I8804: Consumer | J8804: United States | K8804: Oklahoma City | L8804: Oklahoma | M8804: 73120 | N8804: Central | O8804: FUR-BO-10003966 | P8804: Furniture | Q8804: Bookcases | R8804: Sauder Facets Collection Library, Sky Alder Finish | S8804: 341.96 | T8804: 2 | U8804: 0 | V8804: 54.7136
A8805: 8804 | B8805: CA-2011-157644 | C8805: =YEAR(Data!$D8805) -> 2011 | D8805: 40908 | E8805: 40909 | F8805: First Class | G8805: AH-10030 | H8805: Aaron Hawkins | I8805: Corporate | J8805: United States | K8805: New York City | L8805: New York | M8805: 10035 | N8805: East | O8805: TEC-AC-10003614 | P8805: Technology | Q8805: Accessories | R8805: Verbatim 25 GB 6x Blu-ray Single Layer Recordable Disc, 10/Pack | S8805: 34.77 | T8805: 3 | U8805: 0 | V8805: 11.4741
A8806: 8805 | B8806: CA-2011-157644 | C8806: =YEAR(Data!$D8806) -> 2011 | D8806: 40908 | E8806: 40909 | F8806: First Class | G8806: AH-10030 | H8806: Aaron Hawkins | I8806: Corporate | J8806: United States | K8806: New York City | L8806: New York | M8806: 10035 | N8806: East | O8806: OFF-LA-10003148 | P8806: Office Supplies | Q8806: Labels | R8806: Avery 51 | S8806: 18.9 | T8806: 3 | U8806: 0 | V8806: 8.694
A8807: 8806 | B8807: US-2014-100398 | C8807: =YEAR(Data!$D8807) -> 2014 | D8807: 41871 | E8807: 41875 | F8807: Standard Class | G8807: DO-13435 | H8807: Denny Ordway | I8807: Consumer | J8807: United States | K8807: Salt Lake City | L8807: Utah | M8807: 84106 | N8807: West | O8807: OFF-BI-10002133 | P8807: Office Supplies | Q8807: Binders | R8807: Wilson Jones Elliptical Ring 3 1/2" Capacity Binders, 800 sheets | S8807: 102.72 | T8807: 3 | U8807: 0.2 | V8807: 37.236
A8808: 8807 | B8808: CA-2013-113082 | C8808: =YEAR(Data!$D8808) -> 2013 | D8808: 41530 | E8808: 41534 | F8808: Standard Class | G8808: MC-17590 | H8808: Matt Collister | I8808: Corporate | J8808: United States | K8808: Utica | L8808: New York | M8808: 13501 | N8808: East | O8808: FUR-FU-10002813 | P8808: Furniture | Q8808: Furnishings | R8808: DAX Contemporary Wood Frame with Silver Metal Mat, Desktop, 11 x 14 Size | S8808: 40.48 | T8808: 2 | U8808: 0 | V8808: 14.5728
A8809: 8808 | B8809: US-2014-110646 | C8809: =YEAR(Data!$D8809) -> 2014 | D8809: 41939 | E8809: 41944 | F8809: Standard Class | G8809: JF-15190 | H8809: Jamie Frazer | I8809: Consumer | J8809: United States | K8809: Philadelphia | L8809: Pennsylvania | M8809: 19134 | N8809: East | O8809: OFF-BI-10004330 | P8809: Office Supplies | Q8809: Binders | R8809: GBC Velobind Prepunched Cover Sets, Regency Series | S8809: 33.282 | T8809: 3 | U8809: 0.7 | V8809: -27.735
A8810: 8809 | B8810: US-2014-110646 | C8810: =YEAR(Data!$D8810) -> 2014 | D8810: 41939 | E8810: 41944 | F8810: Standard Class | G8810: JF-15190 | H8810: Jamie Frazer | I8810: Consumer | J8810: United States | K8810: Philadelphia | L8810: Pennsylvania | M8810: 19134 | N8810: East | O8810: TEC-PH-10002807 | P8810: Technology | Q8810: Phones | R8810: Motorla HX550 Universal Bluetooth Headset | S8810: 118.65 | T8810: 5 | U8810: 0.4 | V8810: 19.775
A8811: 8810 | B8811: US-2014-110646 | C8811: =YEAR(Data!$D8811) -> 2014 | D8811: 41939 | E8811: 41944 | F8811: Standard Class | G8811: JF-15190 | H8811: Jamie Frazer | I8811: Consumer | J8811: United States | K8811: Philadelphia | L8811: Pennsylvania | M8811: 19134 | N8811: East | O8811: OFF-LA-10001404 | P8811: Office Supplies | Q8811: Labels | R8811: Avery 517 | S8811: 14.76 | T8811: 5 | U8811: 0.2 | V8811: 4.9815
A8812: 8811 | B8812: CA-2014-120614 | C8812: =YEAR(Data!$D8812) -> 2014 | D8812: 41790 | E8812: 41795 | F8812: Standard Class | G8812: SM-20950 | H8812: Suzanne McNair | I8812: Corporate | J8812: United States | K8812: Los Angeles | L8812: California | M8812: 90004 | N8812: West | O8812: OFF-PA-10004911 | P8812: Office Supplies | Q8812: Paper | R8812: Rediform S.O.S. 1-Up Phone Message Bk, 4-1/4x3-1/16 Bk, 1 Form/Pg, 40 Messages/Bk, 3/Pk | S8812: 37.52 | T8812: 4 | U8812: 0 | V8812: 18.0096
... A9147: 9146 | B9147: CA-2012-126970 | C9147: =YEAR(Data!$D9147) -> 2012 | D9147: 41172 | E9147: 41176 | F9147: Standard Class | G9147: TP-21130 | H9147: Theone Pippenger | I9147: Consumer | J9147: United States | K9147: Naperville | L9147: Illinois | M9147: 60540 | N9147: Central | O9147: OFF-BI-10000138 | P9147: Office Supplies | Q9147: Binders | R9147: Acco Translucent Poly Ring Binders | S9147: 2.808 | T9147: 3 | U9147: 0.8 | V9147: -4.4928
A9148: 9147 | B9148: US-2013-165505 | C9148: =YEAR(Data!$D9148) -> 2013 | D9148: 41297 | E9148: 41301 | F9148: Standard Class | G9148: CB-12535 | H9148: Claudia Bergmann | I9148: Corporate | J9148: United States | K9148: Burlington | L9148: Vermont | M9148: 05408 | N9148: East | O9148: TEC-AC-10002926 | P9148: Technology | Q9148: Accessories | R9148: Logitech Wireless Marathon Mouse M705 | S9148: 99.98 | T9148: 2 | U9148: 0 | V9148: 42.9914
A9149: 9148 | B9149: US-2013-165505 | C9149: =YEAR(Data!$D9149) -> 2013 | D9149: 41297 | E9149: 41301 | F9149: Standard Class | G9149: CB-12535 | H9149: Claudia Bergmann | I9149: Corporate | J9149: United States | K9149: Burlington | L9149: Vermont | M9149: 05408 | N9149: East | O9149: OFF-AR-10003477 | P9149: Office Supplies | Q9149: Art | R9149: 4009 Highlighters | S9149: 8.04 | T9149: 6 | U9149: 0 | V9149: 2.7336
A9150: 9149 | B9150: US-2013-165505 | C9150: =YEAR(Data!$D9150) -> 2013 | D9150: 41297 | E9150: 41301 | F9150: Standard Class | G9150: CB-12535 | H9150: Claudia Bergmann | I9150: Corporate | J9150: United States | K9150: Burlington | L9150: Vermont | M9150: 05408 | N9150: East | O9150: OFF-ST-10001526 | P9150: Office Supplies | Q9150: Storage | R9150: Iceberg Mobile Mega Data/Printer Cart | S9150: 1564.29 | T9150: 13 | U9150: 0 | V9150: 406.7154
A9151: 9150 | B9151: US-2011-157070 | C9151: =YEAR(Data!$D9151) -> 2011 | D9151: 40695 | E9151: 40700 | F9151: Standard Class | G9151: QJ-19255 | H9151: Quincy Jones | I9151: Corporate | J9151: United States | K9151: Detroit | L9151: Michigan | M9151: 48234 | N9151: Central | O9151: OFF-BI-10001765 | P9151: Office Supplies | Q9151: Binders | R9151: Wilson Jones Heavy-Duty Casebound Ring Binders with Metal Hinges | S9151: 138.56 | T9151: 4 | U9151: 0 | V9151: 66.5088
A9152: 9151 | B9152: US-2011-157070 | C9152: =YEAR(Data!$D9152) -> 2011 | D9152: 40695 | E9152: 40700 | F9152: Standard Class | G9152: QJ-19255 | H9152: Quincy Jones | I9152: Corporate | J9152: United States | K9152: Detroit | L9152: Michigan | M9152: 48234 | N9152: Central | O9152: OFF-AP-10004859 | P9152: Office Supplies | Q9152: Appliances | R9152: Acco 6 Outlet Guardian Premium Surge Suppressor | S9152: 65.52 | T9152: 5 | U9152: 0.1 | V9152: 12.376
A9153: 9152 | B9153: US-2012-106873 | C9153: =YEAR(Data!$D9153) -> 2012 | D9153: 41176 | E9153: 41181 | F9153: Second Class | G9153: KM-16720 | H9153: Kunst Miller | I9153: Consumer | J9153: United States | K9153: Avondale | L9153: Arizona | M9153: 85323 | N9153: West | O9153: OFF-AR-10003179 | P9153: Office Supplies | Q9153: Art | R9153: Dixon Ticonderoga Core-Lock Colored Pencils | S9153: 14.576 | T9153: 2 | U9153: 0.2 | V9153: 2.3686
A9154: 9153 | B9154: US-2012-106873 | C9154: =YEAR(Data!$D9154) -> 2012 | D9154: 41176 | E9154: 41181 | F9154: Second Class | G9154: KM-16720 | H9154: Kunst Miller | I9154: Consumer | J9154: United States | K9154: Avondale | L9154: Arizona | M9154: 85323 | N9154: West | O9154: TEC-AC-10002345 | P9154: Technology | Q9154: Accessories | R9154: HP Standard 104 key PS/2 Keyboard | S9154: 23.2 | T9154: 2 | U9154: 0.2 | V9154: 1.45
A9155: 9154 | B9155: US-2012-106873 | C9155: =YEAR(Data!$D9155) -> 2012 | D9155: 41176 | E9155: 41181 | F9155: Second Class | G9155: KM-16720 | H9155: Kunst Miller | I9155: Consumer | J9155: United States | K9155: Avondale | L9155: Arizona | M9155: 85323 | N9155: West | O9155: OFF-AR-10001246 | P9155: Office Supplies | Q9155: Art | R9155: Newell 317 | S9155: 16.464 | T9155: 7 | U9155: 0.2 | V9155: 1.8522
A9156: 9155 | B9156: CA-2013-132990 | C9156: =YEAR(Data!$D9156) -> 2013 | D9156: 41488 | E9156: 41490 | F9156: Second Class | G9156: KM-16660 | H9156: Khloe Miller | I9156: Consumer | J9156: United States | K9156: Philadelphia | L9156: Pennsylvania | M9156: 19140 | N9156: East | O9156: FUR-FU-10004864 | P9156: Furniture | Q9156: Furnishings | R9156: Eldon 500 Class Desk Accessories | S9156: 19.312 | T9156: 2 | U9156: 0.2 | V9156: 3.1382
A9157: 9156 | B9157: CA-2011-102645 | C9157: =YEAR(Data!$D9157) -> 2011 | D9157: 40567 | E9157: 40572 | F9157: Standard Class | G9157: IM-15055 | H9157: Ionia McGrath | I9157: Consumer | J9157: United States | K9157: Las Vegas | L9157: Nevada | M9157: 89115 | N9157: West | O9157: OFF-PA-10001804 | P9157: Office Supplies | Q9157: Paper | R9157: Xerox 195 | S9157: 40.08 | T9157: 6 | U9157: 0 | V9157: 19.2384
A9158: 9157 | B9158: CA-2011-134215 | C9158: =YEAR(Data!$D9158) -> 2011 | D9158: 40759 | E9158: 40763 | F9158: Standard Class | G9158: ML-17395 | H9158: Marina Lichtenstein | I9158: Corporate | J9158: United States | K9158: Bangor | L9158: Maine | M9158: 4401 | N9158: East | O9158: OFF-AP-10001271 | P9158: Office Supplies | Q9158: Appliances | R9158: Eureka The Boss Cordless Rechargeable Stick Vac | S9158: 101.96 | T9158: 2 | U9158: 0 | V9158: 27.5292
A9159: 9158 | B9159: CA-2011-134215 | C9159: =YEAR(Data!$D9159) -> 2011 | D9159: 40759 | E9159: 40763 | F9159: Standard Class | G9159: ML-17395 | H9159: Marina Lichtenstein | I9159: Corporate | J9159: United States | K9159: Bangor | L9159: Maine | M9159: 4401 | N9159: East | O9159: OFF-PA-10004353 | P9159: Office Supplies | Q9159: Paper | R9159: Southworth 25% Cotton Premium Laser Paper and Envelopes | S9159: 259.74 | T9159: 13 | U9159: 0 | V9159: 124.6752
A9160: 9159 | B9160: CA-2011-134215 | C9160: =YEAR(Data!$D9160) -> 2011 | D9160: 40759 | E9160: 40763 | F9160: Standard Class | G9160: ML-17395 | H9160: Marina Lichtenstein | I9160: Corporate | J9160: United States | K9160: Bangor | L9160: Maine | M9160: 4401 | N9160: East | O9160: TEC-AC-10002473 | P9160: Technology | Q9160: Accessories | R9160: Maxell 4.7GB DVD-R | S9160: 255.42 | T9160: 9 | U9160: 0 | V9160: 104.7222
A9161: 9160 | B9161: CA-2013-118934 | C9161: =YEAR(Data!$D9161) -> 2013 | D9161: 41496 | E9161: 41501 | F9161: Standard Class | G9161: GH-14410 | H9161: Gary Hansen | I9161: Home Office | J9161: United States | K9161: Hendersonville | L9161: Tennessee | M9161: 37075 | N9161: South | O9161: OFF-BI-10003314 | P9161: Office Supplies | Q9161: Binders | R9161: Tuff Stuff Recycled Round Ring Binders | S9161: 4.338 | T9161: 3 | U9161: 0.7 | V9161: -3.0366
A9162: 9161 | B9162: CA-2013-118934 | C9162: =YEAR(Data!$D9162) -> 2013 | D9162: 41496 | E9162: 41501 | F9162: Standard Class | G9162: GH-14410 | H9162: Gary Hansen | I9162: Home Office | J9162: United States | K9162: Hendersonville | L9162: Tennessee | M9162: 37075 | N9162: South | O9162: OFF-BI-10004465 | P9162: Office Supplies | Q9162: Binders | R9162: Avery Durable Slant Ring Binders | S9162: 11.88 | T9162: 5 | U9162: 0.7 | V9162: -7.92
... A9387: 9386 | B9387: CA-2014-163097 | C9387: =YEAR(Data!$D9387) -> 2014 | D9387: 41879 | E9387: 41883 | F9387: Standard Class | G9387: SF-20200 | H9387: Sarah Foster | I9387: Consumer | J9387: United States | K9387: Mesa | L9387: Arizona | M9387: 85204 | N9387: West | O9387: FUR-FU-10004973 | P9387: Furniture | Q9387: Furnishings | R9387: Flat Face Poster Frame | S9387: 120.576 | T9387: 8 | U9387: 0.2 | V9387: 33.1584
A9388: 9387 | B9388: US-2014-127292 | C9388: =YEAR(Data!$D9388) -> 2014 | D9388: 41659 | E9388: 41663 | F9388: Standard Class | G9388: RM-19375 | H9388: Raymond Messe | I9388: Consumer | J9388: United States | K9388: Burlington | L9388: Vermont | M9388: 05408 | N9388: East | O9388: OFF-PA-10000157 | P9388: Office Supplies | Q9388: Paper | R9388: Xerox 191 | S9388: 79.92 | T9388: 4 | U9388: 0 | V9388: 37.5624
A9389: 9388 | B9389: US-2014-127292 | C9389: =YEAR(Data!$D9389) -> 2014 | D9389: 41659 | E9389: 41663 | F9389: Standard Class | G9389: RM-19375 | H9389: Raymond Messe | I9389: Consumer | J9389: United States | K9389: Burlington | L9389: Vermont | M9389: 05408 | N9389: East | O9389: OFF-PA-10001970 | P9389: Office Supplies | Q9389: Paper | R9389: Xerox 1881 | S9389: 12.28 | T9389: 1 | U9389: 0 | V9389: 5.7716
A9390: 9389 | B9390: US-2014-127292 | C9390: =YEAR(Data!$D9390) -> 2014 | D9390: 41659 | E9390: 41663 | F9390: Standard Class | G9390: RM-19375 | H9390: Raymond Messe | I9390: Consumer | J9390: United States | K9390: Burlington | L9390: Vermont | M9390: 05408 | N9390: East | O9390: OFF-AP-10000828 | P9390: Office Supplies | Q9390: Appliances | R9390: Avanti 4.4 Cu. Ft. Refrigerator | S9390: 542.94 | T9390: 3 | U9390: 0 | V9390: 152.0232
A9391: 9390 | B9391: US-2014-127292 | C9391: =YEAR(Data!$D9391) -> 2014 | D9391: 41659 | E9391: 41663 | F9391: Standard Class | G9391: RM-19375 | H9391: Raymond Messe | I9391: Consumer | J9391: United States | K9391: Burlington | L9391: Vermont | M9391: 05408 | N9391: East | O9391: OFF-EN-10001509 | P9391: Office Supplies | Q9391: Envelopes | R9391: Poly String Tie Envelopes | S9391: 2.04 | T9391: 1 | U9391: 0 | V9391: 0.9588
A9392: 9391 | B9392: CA-2012-163734 | C9392: =YEAR(Data!$D9392) -> 2012 | D9392: 41079 | E9392: 41084 | F9392: Standard Class | G9392: KM-16375 | H9392: Katherine Murray | I9392: Home Office | J9392: United States | K9392: Houston | L9392: Texas | M9392: 77070 | N9392: Central | O9392: OFF-ST-10003692 | P9392: Office Supplies | Q9392: Storage | R9392: Recycled Steel Personal File for Hanging File Folders | S9392: 228.92 | T9392: 5 | U9392: 0.2 | V9392: 14.3075
A9393: 9392 | B9393: CA-2014-162474 | C9393: =YEAR(Data!$D9393) -> 2014 | D9393: 41712 | E9393: 41715 | F9393: First Class | G9393: FH-14275 | H9393: Frank Hawley | I9393: Corporate | J9393: United States | K9393: Aurora | L9393: Illinois | M9393: 60505 | N9393: Central | O9393: TEC-PH-10004700 | P9393: Technology | Q9393: Phones | R9393: PowerGen Dual USB Car Charger | S9393: 7.992 | T9393: 1 | U9393: 0.2 | V9393: 2.5974
A9394: 9393 | B9394: CA-2012-130848 | C9394: =YEAR(Data!$D9394) -> 2012 | D9394: 41207 | E9394: 41207 | F9394: Same Day | G9394: DG-13300 | H9394: Deirdre Greer | I9394: Corporate | J9394: United States | K9394: Denver | L9394: Colorado | M9394: 80219 | N9394: West | O9394: FUR-CH-10000422 | P9394: Furniture | Q9394: Chairs | R9394: Global Highback Leather Tilter in Burgundy | S9394: 582.336 | T9394: 8 | U9394: 0.2 | V9394: -29.1168
A9395: 9394 | B9395: CA-2011-125997 | C9395: =YEAR(Data!$D9395) -> 2011 | D9395: 40806 | E9395: 40809 | F9395: First Class | G9395: MW-18220 | H9395: Mitch Webber | I9395: Consumer | J9395: United States | K9395: New York City | L9395: New York | M9395: 10011 | N9395: East | O9395: TEC-PH-10003484 | P9395: Technology | Q9395: Phones | R9395: Ooma Telo VoIP Home Phone System | S9395: 629.95 | T9395: 5 | U9395: 0 | V9395: 157.4875
A9396: 9395 | B9396: CA-2011-125997 | C9396: =YEAR(Data!$D9396) -> 2011 | D9396: 40806 | E9396: 40809 | F9396: First Class | G9396: MW-18220 | H9396: Mitch Webber | I9396: Consumer | J9396: United States | K9396: New York City | L9396: New York | M9396: 10011 | N9396: East | O9396: FUR-CH-10001394 | P9396: Furniture | Q9396: Chairs | R9396: Global Leather Executive Chair | S9396: 631.782 | T9396: 2 | U9396: 0.1 | V9396: 140.396
A9397: 9396 | B9397: CA-2011-125997 | C9397: =YEAR(Data!$D9397) -> 2011 | D9397: 40806 | E9397: 40809 | F9397: First Class | G9397: MW-18220 | H9397: Mitch Webber | I9397: Consumer | J9397: United States | K9397: New York City | L9397: New York | M9397: 10011 | N9397: East | O9397: FUR-BO-10002213 | P9397: Furniture | Q9397: Bookcases | R9397: DMI Eclipse Executive Suite Bookcases | S9397: 801.568 | T9397: 2 | U9397: 0.2 | V9397: -10.0196
A9398: 9397 | B9398: CA-2011-125997 | C9398: =YEAR(Data!$D9398) -> 2011 | D9398: 40806 | E9398: 40809 | F9398: First Class | G9398: MW-18220 | H9398: Mitch Webber | I9398: Consumer | J9398: United States | K9398: New York City | L9398: New York | M9398: 10011 | N9398: East | O9398: OFF-LA-10002762 | P9398: Office Supplies | Q9398: Labels | R9398: Avery 485 | S9398: 75.18 | T9398: 6 | U9398: 0 | V9398: 35.3346
A9399: 9398 | B9399: CA-2011-125997 | C9399: =YEAR(Data!$D9399) -> 2011 | D9399: 40806 | E9399: 40809 | F9399: First Class | G9399: MW-18220 | H9399: Mitch Webber | I9399: Consumer | J9399: United States | K9399: New York City | L9399: New York | M9399: 10011 | N9399: East | O9399: OFF-AP-10003842 | P9399: Office Supplies | Q9399: Appliances | R9399: Euro-Pro Shark Turbo Vacuum | S9399: 30.98 | T9399: 1 | U9399: 0 | V9399: 8.0548
A9400: 9399 | B9400: CA-2011-125997 | C9400: =YEAR(Data!$D9400) -> 2011 | D9400: 40806 | E9400: 40809 | F9400: First Class | G9400: MW-18220 | H9400: Mitch Webber | I9400: Consumer | J9400: United States | K9400: New York City | L9400: New York | M9400: 10011 | N9400: East | O9400: TEC-PH-10003072 | P9400: Technology | Q9400: Phones | R9400: Panasonic KX-TG9541B DECT 6.0 Digital 2-Line Expandable Cordless Phone With Digital Answering System | S9400: 1349.91 | T9400: 9 | U9400: 0 | V9400: 661.4559
A9401: 9400 | B9401: CA-2013-103128 | C9401: =YEAR(Data!$D9401) -> 2013 | D9401: 41590 | E9401: 41594 | F9401: Standard Class | G9401: SC-20845 | H9401: Sung Chung | I9401: Consumer | J9401: United States | K9401: Arlington Heights | L9401: Illinois | M9401: 60004 | N9401: Central | O9401: OFF-AR-10003394 | P9401: Office Supplies | Q9401: Art | R9401: Newell 332 | S9401: 14.112 | T9401: 6 | U9401: 0.2 | V9401: 1.2348
A9402: 9401 | B9402: CA-2012-167696 | C9402: =YEAR(Data!$D9402) -> 2012 | D9402: 41168 | E9402: 41173 | F9402: Standard Class | G9402: BD-11500 | H9402: Bradley Drucker | I9402: Consumer | J9402: United States | K9402: Newport News | L9402: Virginia | M9402: 23602 | N9402: South | O9402: OFF-EN-10001539 | P9402: Office Supplies | Q9402: Envelopes | R9402: Staples | S9402: 31.12 | T9402: 4 | U9402: 0 | V9402: 14.6264
A9403: 9402 | B9403: CA-2011-159814 | C9403: =YEAR(Data!$D9403) -> 2011 | D9403: 40718 | E9403: 40722 | F9403: Standard Class | G9403: LP-17080 | H9403: Liz Pelletier | I9403: Consumer | J9403: United States | K9403: Tucson | L9403: Arizona | M9403: 85705 | N9403: West | O9403: FUR-FU-10001731 | P9403: Furniture | Q9403: Furnishings | R9403: Acrylic Self-Standing Desk Frames | S9403: 4.272 | T9403: 2 | U9403: 0.2 | V9403: 0.9612
... A9742: 9741 | B9742: CA-2014-129294 | C9742: =YEAR(Data!$D9742) -> 2014 | D9742: 41715 | E9742: 41720 | F9742: Standard Class | G9742: KD-16615 | H9742: Ken Dana | I9742: Corporate | J9742: United States | K9742: Los Angeles | L9742: California | M9742: 90032 | N9742: West | O9742: OFF-AP-10001154 | P9742: Office Supplies | Q9742: Appliances | R9742: Bionaire Personal Warm Mist Humidifier/Vaporizer | S9742: 140.67 | T9742: 3 | U9742: 0 | V9742: 54.8613
A9743: 9742 | B9743: CA-2012-117086 | C9743: =YEAR(Data!$D9743) -> 2012 | D9743: 41221 | E9743: 41225 | F9743: Standard Class | G9743: QJ-19255 | H9743: Quincy Jones | I9743: Corporate | J9743: United States | K9743: Burlington | L9743: Vermont | M9743: 05408 | N9743: East | O9743: FUR-BO-10004834 | P9743: Furniture | Q9743: Bookcases | R9743: Riverside Palais Royal Lawyers Bookcase, Royale Cherry Finish | S9743: 4404.9 | T9743: 5 | U9743: 0 | V9743: 1013.127
A9744: 9743 | B9744: CA-2014-131303 | C9744: =YEAR(Data!$D9744) -> 2014 | D9744: 41972 | E9744: 41976 | F9744: Standard Class | G9744: EP-13915 | H9744: Emily Phan | I9744: Consumer | J9744: United States | K9744: San Diego | L9744: California | M9744: 92037 | N9744: West | O9744: OFF-LA-10001074 | P9744: Office Supplies | Q9744: Labels | R9744: Round Specialty Laser Printer Labels | S9744: 62.65 | T9744: 5 | U9744: 0 | V9744: 29.4455
A9745: 9744 | B9745: CA-2013-137127 | C9745: =YEAR(Data!$D9745) -> 2013 | D9745: 41442 | E9745: 41448 | F9745: Standard Class | G9745: JJ-15445 | H9745: Jennifer Jackson | I9745: Consumer | J9745: United States | K9745: Newark | L9745: Delaware | M9745: 19711 | N9745: East | O9745: OFF-LA-10001641 | P9745: Office Supplies | Q9745: Labels | R9745: Avery 518 | S9745: 9.45 | T9745: 3 | U9745: 0 | V9745: 4.536
A9746: 9745 | B9746: CA-2014-141782 | C9746: =YEAR(Data!$D9746) -> 2014 | D9746: 41661 | E9746: 41665 | F9746: Standard Class | G9746: BE-11410 | H9746: Bobby Elias | I9746: Consumer | J9746: United States | K9746: Aurora | L9746: Illinois | M9746: 60505 | N9746: Central | O9746: OFF-EN-10002230 | P9746: Office Supplies | Q9746: Envelopes | R9746: Airmail Envelopes | S9746: 268.576 | T9746: 4 | U9746: 0.2 | V9746: 90.6444
A9747: 9746 | B9747: CA-2014-137505 | C9747: =YEAR(Data!$D9747) -> 2014 | D9747: 41968 | E9747: 41968 | F9747: Same Day | G9747: BP-11290 | H9747: Beth Paige | I9747: Consumer | J9747: United States | K9747: Los Angeles | L9747: California | M9747: 90008 | N9747: West | O9747: FUR-TA-10000617 | P9747: Furniture | Q9747: Tables | R9747: Hon Practical Foundations 30 x 60 Training Table, Light Gray/Charcoal | S9747: 364.08 | T9747: 2 | U9747: 0.2 | V9747: 9.102
A9748: 9747 | B9748: CA-2014-137505 | C9748: =YEAR(Data!$D9748) -> 2014 | D9748: 41968 | E9748: 41968 | F9748: Same Day | G9748: BP-11290 | H9748: Beth Paige | I9748: Consumer | J9748: United States | K9748: Los Angeles | L9748: California | M9748: 90008 | N9748: West | O9748: FUR-TA-10001676 | P9748: Furniture | Q9748: Tables | R9748: Hon 61000 Series Interactive Training Tables | S9748: 71.088 | T9748: 2 | U9748: 0.2 | V9748: -1.7772
A9749: 9748 | B9749: US-2011-140914 | C9749: =YEAR(Data!$D9749) -> 2011 | D9749: 40858 | E9749: 40862 | F9749: Standard Class | G9749: BH-11710 | H9749: Brosina Hoffman | I9749: Consumer | J9749: United States | K9749: Chicago | L9749: Illinois | M9749: 60653 | N9749: Central | O9749: FUR-FU-10000175 | P9749: Furniture | Q9749: Furnishings | R9749: DAX Wood Document Frame. | S9749: 10.984 | T9749: 2 | U9749: 0.6 | V9749: -7.9634
A9750: 9749 | B9750: US-2011-140914 | C9750: =YEAR(Data!$D9750) -> 2011 | D9750: 40858 | E9750: 40862 | F9750: Standard Class | G9750: BH-11710 | H9750: Brosina Hoffman | I9750: Consumer | J9750: United States | K9750: Chicago | L9750: Illinois | M9750: 60653 | N9750: Central | O9750: FUR-CH-10003379 | P9750: Furniture | Q9750: Chairs | R9750: Global Commerce Series High-Back Swivel/Tilt Chairs | S9750: 797.944 | T9750: 4 | U9750: 0.3 | V9750: -56.996
A9751: 9750 | B9751: CA-2013-158358 | C9751: =YEAR(Data!$D9751) -> 2013 | D9751: 41338 | E9751: 41342 | F9751: Standard Class | G9751: EM-13810 | H9751: Eleni McCrary | I9751: Corporate | J9751: United States | K9751: Dover | L9751: New Hampshire | M9751: 3820 | N9751: East | O9751: TEC-AC-10002567 | P9751: Technology | Q9751: Accessories | R9751: Logitech G602 Wireless Gaming Mouse | S9751: 159.98 | T9751: 2 | U9751: 0 | V9751: 57.5928
A9752: 9751 | B9752: CA-2013-113390 | C9752: =YEAR(Data!$D9752) -> 2013 | D9752: 41559 | E9752: 41563 | F9752: Standard Class | G9752: EP-13915 | H9752: Emily Phan | I9752: Consumer | J9752: United States | K9752: Chicago | L9752: Illinois | M9752: 60610 | N9752: Central | O9752: OFF-AR-10003183 | P9752: Office Supplies | Q9752: Art | R9752: Avery Fluorescent Highlighter Four-Color Set | S9752: 5.344 | T9752: 2 | U9752: 0.2 | V9752: 0.668
A9753: 9752 | B9753: CA-2013-113390 | C9753: =YEAR(Data!$D9753) -> 2013 | D9753: 41559 | E9753: 41563 | F9753: Standard Class | G9753: EP-13915 | H9753: Emily Phan | I9753: Consumer | J9753: United States | K9753: Chicago | L9753: Illinois | M9753: 60610 | N9753: Central | O9753: OFF-AR-10001446 | P9753: Office Supplies | Q9753: Art | R9753: Newell 309 | S9753: 27.72 | T9753: 3 | U9753: 0.2 | V9753: 3.465
...

Sheet layout
A11: `` | B11: =#REF! -> #REF!
